pyUAMMD/__init__.py
pyUAMMD/simulation.py
pyUAMMD/ThirdParty/json.hpp
pyUAMMD/ThirdParty/pybind11_json.hpp
pyUAMMD/appending/__init__.py
pyUAMMD/appending/forceField.py
pyUAMMD/appending/glb.py
pyUAMMD/appending/integrator.py
pyUAMMD/appending/patchyParticles.py
pyUAMMD/appending/simulationStep.py
pyUAMMD/appending/state.py
pyUAMMD/appending/structure.py
pyUAMMD/appending/system.py
pyUAMMD/utils/__init__.py
pyUAMMD/utils/common.py
pyUAMMD/utils/launcher/UAMMDlauncher.cu
pyUAMMD/utils/launcher/__init__.py
pyUAMMD/utils/merging/__init__.py
pyUAMMD/utils/merging/merging.py
pyUAMMD/utils/update/__init__.py
pyUAMMD/utils/update/groups.py
pyUAMMD/utils/update/ids.py
pyUAMMD-1.1.2.dist-info/LICENSE.txt
pyUAMMD-1.1.2.dist-info/METADATA
pyUAMMD-1.1.2.dist-info/WHEEL
pyUAMMD-1.1.2.dist-info/top_level.txt
pyUAMMD-1.1.2.dist-info/RECORD
