Metadata-Version: 2.1
Name: pyUAMMD
Version: 1.1.2
Summary: UAMMD python
Home-page: https://github.com/PabloIbannez/UAMMD-structured
Author-email: Pablo Ibáñez-Freire <p.ibanez.fre@gmail.com>
License: GPL-3.0
Classifier: Development Status :: 3 - Alpha
Classifier: License :: OSI Approved :: GNU General Public License v3 (GPLv3)
Classifier: Programming Language :: Python :: 3
Classifier: Programming Language :: Python :: 3.6
Classifier: Programming Language :: Python :: 3.7
Classifier: Programming Language :: Python :: 3.8
Classifier: Programming Language :: Python :: 3.9
Requires-Python: >=3.7
License-File: LICENSE.txt
Requires-Dist: deepdiff
Requires-Dist: jsbeautifier
Requires-Dist: JFIO
